taktile_client/__init__.py
taktile_client/arrow/__init__.py
taktile_client/arrow/client.py
taktile_client/arrow/endpoint.py
taktile_client/arrow/serialize/__init__.py
taktile_client/arrow/serialize/codecs.py
taktile_client/arrow/serialize/factory.py
taktile_client/arrow/serialize/serializer.py
taktile_client/arrow/serialize/utils.py
taktile_client/arrow/utils.py
taktile_client/client.py
taktile_client/config.py
taktile_client/deployment_api.py
taktile_client/exceptions.py
taktile_client/http_client.py
taktile_client/model.py
taktile_client/py.typed
taktile_client/rest/__init__.py
taktile_client/rest/client.py
taktile_client/rest/endpoint.py
taktile_client/rest/serialize/__init__.py
taktile_client/rest/serialize/dataframe.py
taktile_client/rest/serialize/numpy.py
taktile_client/rest/serialize/pydantic_model.py
taktile_client/rest/serialize/series.py
taktile_client/rest/serialize/utils.py
taktile_client/rest/utils.py
taktile_client/version.py
taktile_client-1.0.9.dist-info/METADATA
taktile_client-1.0.9.dist-info/WHEEL
taktile_client-1.0.9.dist-info/RECORD
