Metadata-Version: 2.1
Name: taktile-client
Version: 1.0.9
Summary: A lightweight client to call models deployed on Taktile.
License: Apache-2.0
Author: Taktile GmbH
Author-email: devops@taktile.com
Requires-Python: >=3.8,<4.0
Classifier: License :: OSI Approved :: Apache Software License
Classifier: Programming Language :: Python :: 3
Classifier: Programming Language :: Python :: 3.8
Classifier: Programming Language :: Python :: 3.9
Classifier: Programming Language :: Python :: 3.10
Classifier: Programming Language :: Python :: 3.11
Provides-Extra: arrow
Requires-Dist: certifi (==2021.10.8) ; extra == "arrow"
Requires-Dist: numpy (>=1.23,<2.0) ; extra == "arrow"
Requires-Dist: packaging (>=23.0,<24.0)
Requires-Dist: pandas (>=1.4,<3.0) ; extra == "arrow"
Requires-Dist: pyarrow (>=8) ; extra == "arrow"
Requires-Dist: pydantic (>=1.8.2,<2.0.0)
Requires-Dist: requests (>=2.26.0,<3.0.0)
Requires-Dist: setuptools (>=0.0.0)
Requires-Dist: taktile-types (>=0.17.0,<1.0.0)
Requires-Dist: tenacity (>=8.0.1,<9.0.0)
